emojiguessr/__init__.py
emojiguessr/__main__.py
emojiguessr/data.py
emojiguessr/quiz.py
emojiguessr/score.py
emojiguessr-1.4.0.dist-info/licenses/LICENSE
examples/demo.py
emojiguessr-1.4.0.dist-info/METADATA
emojiguessr-1.4.0.dist-info/WHEEL
emojiguessr-1.4.0.dist-info/entry_points.txt
emojiguessr-1.4.0.dist-info/top_level.txt
emojiguessr-1.4.0.dist-info/RECORD
