Metadata-Version: 2.4
Name: emojiguessr
Version: 1.4.0
Summary: A tiny emoji guessing game
Author: Team Saffron
License: GNU GENERAL PUBLIC LICENSE
Project-URL: Homepage, https://github.com/swe-students-fall2025/3-python-package-team_saffron
Project-URL: Issues, https://github.com/swe-students-fall2025/3-python-package-team_saffron/issues
Requires-Python: >=3.9
License-File: LICENSE
Dynamic: license-file
